<?xml version="1.0" encoding="UTF-8"?>
<!DOCTYPE suite SYSTEM "https://testng.org/testng-1.0.dtd">
<suite name="Suite" preserve-order="true">
  <test thread-count="5" name="Test">
    <classes>
	    <class name="com.app.scripts.TC00_VerifyTableData"/>
	   <class name="com.app.scripts.TC001_VerifyDateRangeAnd_INSPCheckbox"/>
       <class name="com.app.scripts.TC002_VerifyLabelAnd_Breadcrumb"/>
       <class name="com.app.scripts.TC003_VerifyPatientCount"/>
       <class name="com.app.scripts.TC004_VerifyDaysofCare"/>
       <class name="com.app.scripts.TC005_VerifySNFADM"/>
       <class name="com.app.scripts.TC006_VerifyRTH"/>
       <class name="com.app.scripts.TC007_VerifyEDslashED"/>
       <class name="com.app.scripts.TC008_VerifyACHslashADM"/>
       <class name="com.app.scripts.TC009_VerifyHslash1000"/>
       <class name="com.app.scripts.TC010_VerifyEDslash1000"/>
       <class name="com.app.scripts.TC011_VerifyADMslash1000"/>
       <class name="com.app.scripts.TC012_VerifyPDLTDOC"/>
         <class name="com.app.scripts.End_date_diff_month"/>
	   <class name="com.app.scripts.Months_different"/>
	   <class name="com.app.scripts.Months_same"/>
   </classes>
  </test> <!-- Test -->
</suite> <!-- Suite -->
